{"title": "Quest Means Business", "href": "https://edition.cnn.com/profiles/richard-quest-profile"}
{"title": "The World Right Now", "href": "https://edition.cnn.com/profiles/hala-gorani-profile"}
{"title": "The Business View", "href": "https://edition.cnn.com/profiles/nina-dos-santos"}
{"title": "Quest Means Business", "href": "https://edition.cnn.com/profiles/richard-quest-profile"}
{"title": "The World Right Now", "href": "https://edition.cnn.com/profiles/hala-gorani-profile"}
{"title": "The Business View", "href": "https://edition.cnn.com/profiles/nina-dos-santos"}
{"title": "Quest Means Business", "href": "https://edition.cnn.com/profiles/richard-quest-profile"}
{"title": "The World Right Now", "href": "https://edition.cnn.com/profiles/hala-gorani-profile"}
{"title": "The Business View", "href": "https://edition.cnn.com/profiles/nina-dos-santos"}
{"title": "Quest Means Business", "href": "https://edition.cnn.com/profiles/richard-quest-profile"}
{"title": "The World Right Now", "href": "https://edition.cnn.com/profiles/hala-gorani-profile"}
{"title": "The Business View", "href": "https://edition.cnn.com/profiles/nina-dos-santos"}
{"title": "Quest Means Business", "href": "https://edition.cnn.com/profiles/richard-quest-profile"}
{"title": "The World Right Now", "href": "https://edition.cnn.com/profiles/hala-gorani-profile"}
{"title": "The Business View", "href": "https://edition.cnn.com/profiles/nina-dos-santos"}
